cbsSeatCalendar/__init__.py
cbsSeatCalendar/__main__.py
cbsSeatCalendar/cbsCalendarUpdateClass.py
cbsSeatCalendar-1.1.1.dist-info/METADATA
cbsSeatCalendar-1.1.1.dist-info/WHEEL
cbsSeatCalendar-1.1.1.dist-info/entry_points.txt
cbsSeatCalendar-1.1.1.dist-info/top_level.txt
cbsSeatCalendar-1.1.1.dist-info/RECORD
