Metadata-Version: 2.1
Name: cbsSeatCalendar
Version: 1.1.1
Summary: Simple program to add study seats/group room booking to your calendar for CBS students.
Home-page: https://github.com/EHamre/cbsSeatCalendar
Author: Espen Hamre
Author-email: devespen@outlook.com
License: UNKNOWN
Platform: UNKNOWN
Classifier: Programming Language :: Python :: 3
Classifier: Operating System :: OS Independent
Requires-Python: >=3.7
Requires-Dist: exchangelib
Requires-Dist: datetime
